ptnfc/__init__.py
ptnfc/com_dict.py
ptnfc/rfid_device.py
ptnfc/usb_table.py
ptnfc-1.7.data/data/lib/site-packages/ptnfc/dlls/MasterCom.dll
ptnfc-1.7.data/data/lib/site-packages/ptnfc/dlls/MasterRD.dll
ptnfc-1.7.dist-info/METADATA
ptnfc-1.7.dist-info/WHEEL
ptnfc-1.7.dist-info/top_level.txt
ptnfc-1.7.dist-info/RECORD
